negromate/web/__init__.py
negromate/web/builder.py
negromate/web/commands/__init__.py
negromate/web/commands/build.py
negromate/web/commands/ipfs.py
negromate/web/commands/rsync.py
negromate/web/commands/run.py
negromate.web-1.2.dist-info/LICENSE.txt
negromate.web-1.2.dist-info/METADATA
negromate.web-1.2.dist-info/WHEEL
negromate.web-1.2.dist-info/entry_points.txt
negromate.web-1.2.dist-info/top_level.txt
negromate.web-1.2.dist-info/RECORD
